prefab_cloud_python/__init__.py
prefab_cloud_python/_count_down_latch.py
prefab_cloud_python/_internal_constants.py
prefab_cloud_python/_internal_logging.py
prefab_cloud_python/_requests.py
prefab_cloud_python/_sse_connection_manager.py
prefab_cloud_python/_telemetry.py
prefab_cloud_python/client.py
prefab_cloud_python/config_client.py
prefab_cloud_python/config_client_interface.py
prefab_cloud_python/config_loader.py
prefab_cloud_python/config_parser.py
prefab_cloud_python/config_resolver.py
prefab_cloud_python/config_value_unwrapper.py
prefab_cloud_python/config_value_wrapper.py
prefab_cloud_python/constants.py
prefab_cloud_python/context.py
prefab_cloud_python/context_shape.py
prefab_cloud_python/context_shape_aggregator.py
prefab_cloud_python/encryption.py
prefab_cloud_python/feature_flag_client.py
prefab_cloud_python/log_path_aggregator.py
prefab_cloud_python/logging.py
prefab_cloud_python/options.py
prefab_cloud_python/read_write_lock.py
prefab_cloud_python/semantic_version.py
prefab_cloud_python/simple_criterion_evaluators.py
prefab_cloud_python/weighted_value_resolver.py
prefab_cloud_python/yaml_parser.py
prefab_pb2.py
prefab_cloud_python-0.12.0.dist-info/LICENSE.txt
prefab_cloud_python-0.12.0.dist-info/METADATA
prefab_cloud_python-0.12.0.dist-info/WHEEL
prefab_cloud_python-0.12.0.dist-info/RECORD
