Metadata-Version: 2.3
Name: prefab-cloud-python
Version: 0.12.0
Summary: Python client for Prefab Feature Flags, Dynamic log levels, and Config as a Service: https://www.prefab.cloud
License: MIT
Author: Michael Berkowitz
Author-email: michael.berkowitz@gmail.com
Maintainer: Michael Berkowitz
Maintainer-email: michael.berkowitz@gmail.com
Requires-Python: >=3.9,<4
Classifier: License :: OSI Approved :: MIT License
Classifier: Programming Language :: Python :: 3
Classifier: Programming Language :: Python :: 3.9
Classifier: Programming Language :: Python :: 3.10
Classifier: Programming Language :: Python :: 3.11
Classifier: Programming Language :: Python :: 3.12
Classifier: Programming Language :: Python :: 3.13
Requires-Dist: cachetools (>=5.3.0,<6.0.0)
Requires-Dist: cryptography (>=42.0.0)
Requires-Dist: isodate (>=0.6.1,<0.7.0)
Requires-Dist: mmh3 (>=3.0.0,<5.0.0)
Requires-Dist: protobuf (>=4.21.0)
Requires-Dist: pyyaml (>=6.0.0,<7.0.0)
Requires-Dist: requests (>=2.30.0)
Requires-Dist: sseclient-py (>=1.7.2,<2.0.0)
Requires-Dist: structlog (>=21.1.0)
Requires-Dist: tenacity (>=8.0.0)
Project-URL: Documentation, https://docs.prefab.cloud/docs/sdks/python
Project-URL: Homepage, https://www.prefab.cloud
Project-URL: Repository, https://github.com/prefab-cloud/prefab-cloud-python
